Metadata-Version: 2.1
Name: hexapterygon
Version: 1.1.1
Summary: A user-friendly all-in-one cross-platform, (uni-curses compatible component, module and uitility) software for orchestrating and debloating your Android devices from unwanted pre-installed crap.
Home-page: https://github.com/GiorgosXou/hexapterygon
Author: George Chousos
Author-email: gxousos@gmail.com
License-File: LICENSE
Requires-Dist: uni-curses
Requires-Dist: pure-python-adb
Requires-Dist: PyGithub
